{
    "_subjects":[
    { "_name":"Algoritmi i strukture podataka",
      "_espb": 6
    },
    {
      "_name":"Objektno orijentisano programiranje",
      "_espb": 6
    },
    {
        "_name":"Operativni sistemi",
        "_espb": 6
    },
    {
        "_name":"Geometrija",
        "_espb": 6
    },
    {
        "_name":"Analiza 2",
        "_espb": 6
    },
    {
        "_name":"Konstrukcija i analiza algoritama",
        "_espb": 6
    },
    {
        "_name":"Uvod u veb i internet tehnologije",
        "_espb": 6
    },
    {
        "_name":"Analiza 3",
        "_espb": 6
    },
    {
        "_name":"Algebra 1",
        "_espb": 6
    }

  ]

}


